rstatus/__init__.py
rstatus/main_client.py
rstatus/handlers/__init__.py
rstatus/handlers/bedrock_handler.py
rstatus/handlers/java_handler.py
rstatus/models/__init__.py
rstatus/models/bedrock_server_data.py
rstatus/models/java_server_data.py
rstatus/packets/__init__.py
rstatus/packets/base.py
rstatus/packets/handshake.py
rstatus/packets/login_start.py
rstatus/protocol/__init__.py
rstatus/protocol/version.py
rstatus/utils/__init__.py
rstatus/utils/clear.py
rstatus/utils/client.py
rstatus/utils/compression.py
rstatus/utils/resolver.py
rstatus/utils/response.py
rstatus-0.0.2.dist-info/METADATA
rstatus-0.0.2.dist-info/WHEEL
rstatus-0.0.2.dist-info/top_level.txt
rstatus-0.0.2.dist-info/RECORD
