Metadata-Version: 2.4
Name: rstatus
Version: 0.0.2
Summary: Library to query Minecraft server data
Author-email: Pedro Agustin Vega <pedroagustinvega@proton.me>
Project-URL: Repository, https://github.com/wrrulosdev/rstatus
Classifier: Programming Language :: Python :: 3
Classifier: License :: OSI Approved :: MIT License
Classifier: Operating System :: OS Independent
Requires-Python: >=3.7
Requires-Dist: PySocks>=1.7.1
Requires-Dist: dnspython>=2.7.0
